README.rst
advancedhttpserver.py
setup.py
AdvancedHTTPServer.egg-info/PKG-INFO
AdvancedHTTPServer.egg-info/SOURCES.txt
AdvancedHTTPServer.egg-info/dependency_links.txt
AdvancedHTTPServer.egg-info/top_level.txt